sqlpickle/__init__.py
sqlpickle-0.1.3.dist-info/METADATA
sqlpickle-0.1.3.dist-info/WHEEL
sqlpickle-0.1.3.dist-info/RECORD
