Metadata-Version: 2.1
Name: sqlpickle
Version: 0.1.3
Summary: Simple KV Storage and memoization based on sqlite
License: MIT
Author: Slava Vishnyakov
Author-email: bomboze@gmail.com
Requires-Python: >=3.12,<4.0
Classifier: License :: OSI Approved :: MIT License
Classifier: Programming Language :: Python :: 3
Classifier: Programming Language :: Python :: 3.12
